simpple/__init__.py
simpple/_version.py
simpple/distributions.py
simpple/load.py
simpple/model.py
simpple/plot.py
simpple/utils.py
simpple-0.3.4.dist-info/METADATA
simpple-0.3.4.dist-info/WHEEL
simpple-0.3.4.dist-info/licenses/LICENSE
simpple-0.3.4.dist-info/RECORD
